{
  "document_id": "melville_2020_apl_dielectric_loss_tin_al",
  "source_type": "journal_article",
  "institution": "MIT Lincoln Laboratory",
  "department": null,
  "author": "Melville, Alexander",
  "authors": [
    "Melville, Alexander",
    "Calusine, Greg",
    "Woods, Wayne",
    "Serniak, Kyle",
    "Golden, Evan",
    "Niedzielski, Bethany M.",
    "Kim, David K.",
    "Sevi, Arjan",
    "Yoder, Jonilyn L.",
    "Dauler, Eric A.",
    "Oliver, William D."
  ],
  "advisor": null,
  "year": 2020,
  "title": "Comparison of Dielectric Loss in Titanium Nitride and Aluminum Superconducting Resonators",
  "journal": "Applied Physics Letters",
  "doi": "10.1063/5.0021950",
  "arxiv_id": "2007.07338",
  "url": "https://arxiv.org/abs/2007.07338",
  "download_date": "2026-02-10",
  "file_path": "semiconductor_processing_dataset/raw_documents/papers/superconducting_qubits/materials_studies/melville_2020_apl_dielectric_loss_tin_al.pdf",
  "file_size_mb": 1.78,
  "page_count": 0,
  "domain": [
    "superconducting_qubits"
  ],
  "qubit_types": [],
  "fabrication_topics": [
    "titanium_nitride",
    "aluminum",
    "dielectric_loss",
    "surface_treatment",
    "resonator_fabrication",
    "interface_loss"
  ],
  "keywords": [
    "titanium nitride",
    "TiN",
    "aluminum",
    "CPW resonator",
    "dielectric loss",
    "metal-air interface",
    "substrate-air interface",
    "HF etch",
    "quality factor",
    "surface loss tangent"
  ],
  "has_supplementary": false,
  "supplementary_file_path": null,
  "has_process_flow": false,
  "has_chemical_list": false,
  "has_equipment_list": false,
  "has_parameter_tables": true,
  "fabrication_section": "Methods",
  "page_range": null,
  "extraction_status": {
    "text_extracted": false,
    "docling_complete": false,
    "marker_complete": false,
    "grobid_complete": false,
    "best_extraction": null,
    "chemicals_extracted": false,
    "process_flow_extracted": false,
    "parameters_extracted": false,
    "equipment_extracted": false
  },
  "quality_flags": {
    "ocr_quality": "native_pdf",
    "table_extraction": "unknown",
    "formula_preservation": "unknown",
    "figure_quality": "unknown"
  },
  "quality_assessment": "high_value",
  "priority": "high",
  "notes": "Wave 2 recent fabrication paper. Compares TiN and Al resonator losses. Metal-air interface dominates Al loss; HF etch reduces substrate-air loss.",
  "reviewed_by": null,
  "review_date": null
}
