{
  "document_id": "sears_adam_yale_2013",
  "source_type": "phd_thesis",
  "institution": "Yale University",
  "department": "Applied Physics",
  "author": "Sears, Adam",
  "authors": [
    "Sears, Adam"
  ],
  "advisor": "Schoelkopf",
  "year": 2013,
  "title": "Extending Coherence in Superconducting Qubits: from Microseconds to Milliseconds",
  "journal": null,
  "doi": null,
  "arxiv_id": null,
  "url": "https://rsl.yale.edu/sites/default/files/2024-08/2013-RSL-Thesis-Adam-Sears.pdf",
  "download_date": "2026-02-10",
  "file_path": "semiconductor_processing_dataset/raw_documents/theses/yale/sears_adam_yale_2013.pdf",
  "file_size_mb": 32.67,
  "page_count": 0,
  "domain": [
    "superconducting_qubits"
  ],
  "qubit_types": [],
  "fabrication_topics": [],
  "keywords": [
    "superconducting qubit",
    "fabrication"
  ],
  "has_supplementary": false,
  "supplementary_file_path": null,
  "has_process_flow": false,
  "has_chemical_list": false,
  "has_equipment_list": false,
  "has_parameter_tables": false,
  "fabrication_section": null,
  "page_range": null,
  "extraction_status": {
    "text_extracted": false,
    "docling_complete": false,
    "marker_complete": false,
    "grobid_complete": false,
    "best_extraction": null,
    "chemicals_extracted": false,
    "process_flow_extracted": false,
    "parameters_extracted": false,
    "equipment_extracted": false
  },
  "quality_flags": {
    "ocr_quality": "unknown",
    "table_extraction": "unknown",
    "formula_preservation": "unknown",
    "figure_quality": "unknown"
  },
  "quality_assessment": "high_value",
  "priority": "high",
  "notes": "Yale thesis collection wave 2 - RSL (Schoelkopf group)",
  "reviewed_by": null,
  "review_date": null
}