{
  "document_id": "wu_2017_overlap_junctions",
  "source_type": "journal_article",
  "institution": "NIST / University of Colorado Boulder",
  "department": null,
  "author": "Wu, X.",
  "authors": ["X. Wu", "J. L. Long", "H. S. Ku", "R. E. Lake", "M. Bal", "D. P. Pappas"],
  "advisor": null,
  "year": 2017,
  "title": "Overlap junctions for high coherence superconducting qubits",
  "journal": "Applied Physics Letters",
  "doi": "10.1063/1.4993937",
  "arxiv_id": "1705.08993",
  "url": "https://arxiv.org/abs/1705.08993",
  "download_date": "2026-02-10",
  "file_path": "semiconductor_processing_dataset/raw_documents/papers/superconducting_qubits/fabrication_processes/wu_2017_overlap_junctions.pdf",
  "file_size_mb": 0.89,
  "page_count": 3,
  "domain": ["superconducting_qubits"],
  "qubit_types": ["transmon"],
  "fabrication_topics": ["josephson_junction_fabrication", "overlap_junction", "two_step_lithography", "argon_milling", "normal_angle_evaporation"],
  "keywords": ["overlap junctions", "shadow evaporation alternative", "Ar milling", "two-step lithography", "high coherence", "sub-micron junctions"],
  "has_supplementary": false,
  "supplementary_file_path": null,
  "has_process_flow": true,
  "has_chemical_list": false,
  "has_equipment_list": false,
  "has_parameter_tables": false,
  "fabrication_section": "Methods",
  "page_range": null,
  "extraction_status": {
    "text_extracted": false,
    "docling_complete": false,
    "marker_complete": false,
    "grobid_complete": false,
    "best_extraction": null,
    "chemicals_extracted": false,
    "process_flow_extracted": false,
    "parameters_extracted": false,
    "equipment_extracted": false
  },
  "quality_flags": {
    "ocr_quality": "native_pdf",
    "table_extraction": "unknown",
    "formula_preservation": "unknown",
    "figure_quality": "unknown"
  },
  "quality_assessment": "high_value",
  "priority": "high",
  "notes": "Wave 3 paper collection. Foundational overlap junction technique - alternative to Dolan bridge. Two separate lithography steps with normal-angle evaporation.",
  "reviewed_by": null,
  "review_date": null
}
